safecloud/__init__.py
safecloud/cli.py
safecloud/config.py
safecloud/crypto.py
safecloud/scanner.py
safecloud/utils.py
safecloud-1.0.0.dist-info/licenses/LICENSE
safecloud-1.0.0.dist-info/METADATA
safecloud-1.0.0.dist-info/WHEEL
safecloud-1.0.0.dist-info/entry_points.txt
safecloud-1.0.0.dist-info/top_level.txt
safecloud-1.0.0.dist-info/RECORD
