Metadata-Version: 2.4
Name: safecloud
Version: 1.0.0
Summary: Smart cloud security at a glance
Author: Ekin Ilter Varli
License: GPL-3.0-or-later
Platform: any
Requires-Python: >=3.8
License-File: LICENSE
Requires-Dist: click
Requires-Dist: rich
Requires-Dist: boto3
Requires-Dist: cryptography
Requires-Dist: requests
Requires-Dist: pyfiglet
Requires-Dist: dnspython
Requires-Dist: gpt4all
Dynamic: license
Dynamic: license-file
Dynamic: requires-dist
Dynamic: requires-python
Dynamic: summary
